sesdiff-0.3.2.dist-info/METADATA
sesdiff-0.3.2.dist-info/WHEEL
sesdiff/__init__.py
sesdiff/__init__.pyi
sesdiff/py.typed
sesdiff/sesdiff.cp39-win32.pyd
sesdiff-0.3.2.dist-info/RECORD
