Metadata-Version: 2.3
Name: sesdiff
Version: 0.3.2
Requires-Dist: pytest ; extra == 'test'
Provides-Extra: test
Summary: Generates a shortest edit script (Myers' diff algorithm) to indicate how to get from the strings in column A to the strings in column B. Also provides the edit distance (levenshtein). This is the Python binding.
Keywords: nlp,text-processing,lemmatization,linguistics
Home-Page: https://github.com/proycon/sesdiff/
Author: Maarten van Gompel <proycon@anaproy.nl>
Author-email: Maarten van Gompel <proycon@anaproy.nl>
License: GPL-3.0+
Project-URL: Source Code, https://github.com/proycon/sesdiff
